Automate_GPT/__init__.py
Automate_GPT-1.0.2.dist-info/METADATA
Automate_GPT-1.0.2.dist-info/WHEEL
Automate_GPT-1.0.2.dist-info/top_level.txt
Automate_GPT-1.0.2.dist-info/RECORD
