Metadata-Version: 2.1
Name: Automate_GPT
Version: 1.0.2
Summary: Use Chat GPT Automation
Author: Jenil sheth
Author-email: shethjeniljigneshbhai@gmail.com
Requires-Dist: undetected-chromedriver
Requires-Dist: selenium
Requires-Dist: pyperclip
